{"status":200,"headers":{"date":"Sat, 27 Nov 2021 22:08:58 GMT","server":"ATS/8.0.8","etag":"W/0860c1e63e95143ca82e59a1cf0cd23b","content-type":"image/x-icon","x-object-meta-mtime":"1366740074.0","last-modified":"Thu, 03 Oct 2013 22:29:34 GMT","x-timestamp":"1380839373.79689","vary":"Accept-Encoding","age":"76067","x-cache":"cp3063 hit, cp3059 hit/67833","x-cache-status":"hit-front","server-timing":"cache;desc=\"hit-front\", host;desc=\"cp3059\"","strict-transport-security":"max-age=106384710; includeSubDomains; preload","report-to":"{ \"group\": \"wm_nel\", \"max_age\": 86400, \"endpoints\": [{ \"url\": \"https://intake-logging.wikimedia.org/v1/events?stream=w3c.reportingapi.network_error&schema_uri=/w3c/reportingapi/network_error/1.0.0\" }] }","nel":"{ \"report_to\": \"wm_nel\", \"max_age\": 86400, \"failure_fraction\": 0.05, \"success_fraction\": 0.0}","permissions-policy":"interest-cohort=()","x-client-ip":"89.64.37.224","access-control-allow-origin":"*","access-control-expose-headers":"Age, Date, Content-Length, Content-Range, X-Content-Duration, X-Cache","timing-allow-origin":"*","accept-ranges":"bytes","content-length":"1430","connection":"keep-alive"}}